dask_spark/__init__.py
dask_spark/core.py
dask_spark-0.0.2.dist-info/DESCRIPTION.rst
dask_spark-0.0.2.dist-info/METADATA
dask_spark-0.0.2.dist-info/RECORD
dask_spark-0.0.2.dist-info/WHEEL
dask_spark-0.0.2.dist-info/metadata.json
dask_spark-0.0.2.dist-info/top_level.txt
