Metadata-Version: 2.0
Name: dask-spark
Version: 0.0.2
Summary: Interactions between Dask and Spark
Home-page: UNKNOWN
Author: Matthew Rocklin
Author-email: mrocklin@gmail.com
License: BSD
Platform: UNKNOWN
Requires-Dist: dask (>=0.14.0)
Requires-Dist: distributed (>=1.16.0)
